LICENSE.md
MANIFEST.in
README.rst
pyproject.toml
setup.cfg
setup.py
django_slick_reporting.egg-info/PKG-INFO
django_slick_reporting.egg-info/SOURCES.txt
django_slick_reporting.egg-info/SOURCES.txt.py
django_slick_reporting.egg-info/dependency_links.txt
django_slick_reporting.egg-info/dependency_links.txt.py
django_slick_reporting.egg-info/requires.txt
django_slick_reporting.egg-info/requires.txt.py
django_slick_reporting.egg-info/top_level.txt
django_slick_reporting.egg-info/top_level.txt.py
slick_reporting/__init__.py
slick_reporting/app_settings.py
slick_reporting/apps.py
slick_reporting/decorators.py
slick_reporting/fields.py
slick_reporting/form_factory.py
slick_reporting/forms.py
slick_reporting/generator.py
slick_reporting/helpers.py
slick_reporting/registry.py
slick_reporting/views.py
slick_reporting/static/slick_reporting/slick_reporting.chartsjs.js
slick_reporting/static/slick_reporting/slick_reporting.datatable.js
slick_reporting/static/slick_reporting/slick_reporting.highchart.js
slick_reporting/static/slick_reporting/slick_reporting.js
slick_reporting/static/slick_reporting/slick_reporting.report_loader.js
slick_reporting/templates/slick_reporting/base.html
slick_reporting/templates/slick_reporting/js_resources.html
slick_reporting/templates/slick_reporting/report.html
slick_reporting/templates/slick_reporting/widget_template.html
slick_reporting/templatetags/__init__.py
slick_reporting/templatetags/slick_reporting_tags.py